folio_user_bulk_edit-1.0.0.dist-info/METADATA
folio_user_bulk_edit-1.0.0.dist-info/WHEEL
folio_user_bulk_edit-1.0.0.dist-info/entry_points.txt
folio_user_bulk_edit-1.0.0.dist-info/licenses/LICENSE
folio_user_bulk_edit/__init__.py
folio_user_bulk_edit/__main__.py
folio_user_bulk_edit/_cli_log.py
folio_user_bulk_edit/cli.py
folio_user_bulk_edit/commands/__init__.py
folio_user_bulk_edit/commands/check.py
folio_user_bulk_edit/commands/user_import.py
folio_user_bulk_edit/data.py
folio_user_bulk_edit/folio.py
folio_user_bulk_edit/schemas.py
folio_user_bulk_edit-1.0.0.dist-info/RECORD
