Metadata-Version: 2.1
Name: folio-user-bulk-edit
Version: 1.0.0
Summary: Initiates, monitors, and reports on bulk user operations in FOLIO.
Author-Email: Katherine Bargar <kbargar@fivecolleges.edu>
License: Apache-2.0
Requires-Python: >=3.10
Requires-Dist: polars<1.23
Requires-Dist: pandera[polars]>=0.19
Requires-Dist: pyfolioclient>=0.1.2
Requires-Dist: httpx>=0.28.1
